polyA/__init__.py
polyA/__main__.py
polyA/_app.py
polyA/_options.py
polyA/_runners.py
polyA/_version.py
polyA/alignment.py
polyA/calc_repeat_scores.py
polyA/calculate_score.py
polyA/collapse_matrices.py
polyA/confidence_cm.py
polyA/constants.py
polyA/edges.py
polyA/exceptions.py
polyA/extract_nodes.py
polyA/fill_align_matrix.py
polyA/fill_confidence_matrix.py
polyA/fill_consensus_position_matrix.py
polyA/fill_node_confidence.py
polyA/fill_path_graph.py
polyA/fill_probability_matrix.py
polyA/fill_support_matrix.py
polyA/get_path.py
polyA/lambda_provider.py
polyA/load_alignments.py
polyA/matrices.py
polyA/output.py
polyA/pad_sequences.py
polyA/performance.py
polyA/polya-soda.js
polyA/print_helpers.py
polyA/printers.py
polyA/prior_counts.py
polyA/substitution_matrix.py
polyA/sum_repeat_scores.py
polyA/ultra_provider.py
polyA/converters/__init__.py
polyA/converters/cm_to_stockholm.py
polyA/converters/rm_to_stockholm.py
polya-1.3.2.dist-info/entry_points.txt
polya-1.3.2.dist-info/LICENSE
polya-1.3.2.dist-info/WHEEL
polya-1.3.2.dist-info/METADATA
polya-1.3.2.dist-info/RECORD
