Metadata-Version: 2.1
Name: polyA
Version: 1.3.2
Summary: PolyA is a sequence annotation adjudicator.
Home-page: https://github.com/TravisWheelerLab/polyA
Author: Kaitlin Carey
Author-email: kaitlin1.carey@umontana.edu
Maintainer: Jack Roddy
Maintainer-email: jroddy@arizona.edu
Classifier: Programming Language :: Python :: 3.7
Classifier: Programming Language :: Python :: 3.8
Classifier: Programming Language :: Python :: 3.9
Classifier: License :: OSI Approved :: BSD License
Classifier: Topic :: Scientific/Engineering :: Bio-Informatics
Requires-Dist: requests >= 2.27.1
